README.md
license.txt
setup.py
electricity_predictor/__init__.py
electricity_predictor/predictor.py
electricity_predictor.egg-info/PKG-INFO
electricity_predictor.egg-info/SOURCES.txt
electricity_predictor.egg-info/dependency_links.txt
electricity_predictor.egg-info/requires.txt
electricity_predictor.egg-info/top_level.txt
tests/__init__.py
tests/test_predictor.py